tjpy_subprocess_util/__init__.py
tjpy_subprocess_util/exception.py
tjpy_subprocess_util/execution.py
tjpy_subprocess_util/py.typed
tjpy_subprocess_util-0.1.3.dist-info/LICENSE
tjpy_subprocess_util-0.1.3.dist-info/METADATA
tjpy_subprocess_util-0.1.3.dist-info/WHEEL
tjpy_subprocess_util-0.1.3.dist-info/top_level.txt
tjpy_subprocess_util-0.1.3.dist-info/RECORD
